poeditor_sync/__init__.py
poeditor_sync/cmd.py
poeditor_sync/models.py
poeditor_sync/sync.py
poeditor_sync-0.6.dist-info/LICENSE
poeditor_sync-0.6.dist-info/METADATA
poeditor_sync-0.6.dist-info/WHEEL
poeditor_sync-0.6.dist-info/entry_points.txt
poeditor_sync-0.6.dist-info/top_level.txt
poeditor_sync-0.6.dist-info/RECORD
