Metadata-Version: 2.1
Name: poeditor-sync
Version: 0.6
Summary: Command line client for POEditor service
Home-page: https://github.com/mick88/poeditor-sync
Author: Michal Dabski
Author-email: contact@michaldabski.com
License: MIT
Project-URL: Source, https://github.com/mick88/poeditor-sync
Project-URL: Tracker, https://github.com/mick88/poeditor-sync/issues
Project-URL: Changelog, https://github.com/mick88/poeditor-sync/blob/master/HISTORY.txt
Project-URL: Example configuration, https://github.com/mick88/poeditor-sync/blob/master/example/poeditor.yml
Project-URL: POEditor, https://poeditor.com/
Platform: UNKNOWN
Classifier: Development Status :: 4 - Beta
Classifier: Programming Language :: Python :: 3 :: Only
Classifier: Programming Language :: Python :: 3
Classifier: Programming Language :: Python :: 3.7
Classifier: Programming Language :: Python :: 3.8
Classifier: Programming Language :: Python :: 3.9
Classifier: Programming Language :: Python :: 3.10
Classifier: Programming Language :: Python :: 3.11
Classifier: Environment :: Console
Classifier: Intended Audience :: Developers
Classifier: License :: OSI Approved :: MIT License
Classifier: Natural Language :: English
Classifier: Operating System :: OS Independent
Classifier: Topic :: Software Development :: Internationalization
Classifier: Topic :: Utilities
Requires-Dist: click >=8
Requires-Dist: poeditor
Requires-Dist: pyyaml
